Metadata-Version: 1.1
Name: vapix
Version: 0.1.1
Summary: Cli to handle open doors
Home-page: UNKNOWN
Author: jadson179
Author-email: UNKNOWN
License: MIT
Platform: UNKNOWN
Classifier: Programming Language :: Python
Classifier: Programming Language :: Python :: 3.8
